[
{
    "model": "auth.user",
    "fields": {
        "password": "pbkdf2_sha256$390000$kHBNytxdkr1US7dE6uENJG$G+Vbo4g3AOoMupUA6nG7M7QO7nFtX85rsg27sHv+u+M=",
        "last_login": "2023-01-24T11:26:50.437Z",
        "is_superuser": true,
        "username": "admin",
        "first_name": "",
        "last_name": "",
        "email": "admin@admin.com",
        "is_staff": true,
        "is_active": true,
        "date_joined": "2023-01-20T23:47:40.117Z",
        "groups": [],
        "user_permissions": []
    }
},
{
    "model": "auth.user",
    "fields": {
        "password": "pbkdf2_sha256$390000$zeezEhjIfRuz0VjjpMyAAo$K6Iuf9u01DJBLLVzP5GRIMe4/V/hGvbJtT8cCfgyLJs=",
        "last_login": "2023-01-24T12:11:21.760Z",
        "is_superuser": false,
        "username": "user",
        "first_name": "jan",
        "last_name": "kowalski",
        "email": "",
        "is_staff": false,
        "is_active": true,
        "date_joined": "2023-01-24T08:10:31Z",
        "groups": [],
        "user_permissions": []
    }
},
{
    "model": "auth.user",
    "fields": {
        "password": "pbkdf2_sha256$390000$AhGVyLk9wZIqyawL04MXFx$MZu+S14KAWEKV3VfFfWY+B2kanal9WqL+1N4qV6n2Po=",
        "last_login": null,
        "is_superuser": false,
        "username": "user2",
        "first_name": "",
        "last_name": "",
        "email": "",
        "is_staff": false,
        "is_active": true,
        "date_joined": "2023-01-24T08:15:38.764Z",
        "groups": [],
        "user_permissions": []
    }
},
{
    "model": "sessions.session",
    "pk": "1hhwk5ygc17toeqkgr023y7owqwbb5v0",
    "fields": {
        "session_data": ".eJxVjEEOwiAQRe_C2hDKILQu3XsGMsNMpWogKe3KeHfbpAvdvvf-f6uI65Lj2mSOE6uLAnX6ZYTpKWUX_MByrzrVsswT6T3Rh236Vlle16P9O8jY8rZ26GFAI5ZGojBAsGT9CMkl8XBmJOE-dMl6m0wHvkcxxBtyjoMwiPp8AfaVOIs:1pK4m7:_eadevD3rz6wrAl0_t1yiNLYV4xauKFkfrTSmUF3T18",
        "expire_date": "2023-02-06T21:54:47.499Z"
    }
},
{
    "model": "sessions.session",
    "pk": "5kbpvquxdh6vuco85wveuecykyovmsww",
    "fields": {
        "session_data": ".eJxVjEEOwiAQRe_C2pBSkDIu3fcMZAZmpGpoUtqV8e7apAvd_vfef6mI21ri1niJU1YX5dTpdyNMD647yHest1mnua7LRHpX9EGbHufMz-vh_h0UbOVbQ-Cz71I3-NQjAAUQx4Ox1osDw0xkJaBFY7wlYYQ-BINMAuITuaTeH-FIOHs:1pKI93:VZifQPstYCV6IhsSN7_dJMYLz4ZQzLZlGZ9V4g84rS4",
        "expire_date": "2023-02-07T12:11:21.764Z"
    }
},
{
    "model": "sessions.session",
    "pk": "7jhjlbc19odtj3j5wr7m6slq7uhxcr77",
    "fields": {
        "session_data": ".eJxVjEEOwiAQRe_C2hDKILQu3XsGMsNMpWogKe3KeHfbpAvdvvf-f6uI65Lj2mSOE6uLAnX6ZYTpKWUX_MByrzrVsswT6T3Rh236Vlle16P9O8jY8rZ26GFAI5ZGojBAsGT9CMkl8XBmJOE-dMl6m0wHvkcxxBtyjoMwiPp8AfaVOIs:1pK4P4:xAZWhYgU0zVHiPKMGWhrr599MBwMD_IHUvvSjmyHZyo",
        "expire_date": "2023-02-06T21:30:58.929Z"
    }
},
{
    "model": "sessions.session",
    "pk": "8mvcjba39wqwanjeb3cn1wnbv5w1bo43",
    "fields": {
        "session_data": ".eJxVjEEOwiAQRe_C2pBSkDIu3fcMZAZmpGpoUtqV8e7apAvd_vfef6mI21ri1niJU1YX5dTpdyNMD647yHest1mnua7LRHpX9EGbHufMz-vh_h0UbOVbQ-Cz71I3-NQjAAUQx4Ox1osDw0xkJaBFY7wlYYQ-BINMAuITuaTeH-FIOHs:1pKHvS:vJCUJDwAqa0YcMCXnTp6HH4gw3RDPcpwIXu4DwW_Ca8",
        "expire_date": "2023-02-07T11:57:18.553Z"
    }
},
{
    "model": "sessions.session",
    "pk": "fuisy2q28qxfi2rrdjvq3i5esdpqsja6",
    "fields": {
        "session_data": ".eJxVjEEOwiAQRe_C2pBpCzPg0r1nIEMHpWogKe3KeHfbpAvdvvf-f6vA65LD2tIcJlFn1anTL4s8PlPZhTy43Ksea1nmKeo90Ydt-lolvS5H-3eQueVtbcEly5GBUoxDDx6RjTWuI_IgRBtDMeDZ3AQAnXU4xBGsJDLeYa8-X8PeNro:1pJLlg:kE_85V2twZiCytNCov7WWJxqLNbMn2LnsEk0WDYvo6A",
        "expire_date": "2023-02-04T21:51:20.810Z"
    }
},
{
    "model": "familybudgetapp.budget",
    "pk": 74,
    "fields": {
        "name": "Savings",
        "description": null,
        "owner": [
            "user"
        ]
    }
},
{
    "model": "familybudgetapp.budget",
    "pk": 75,
    "fields": {
        "name": "Main",
        "description": null,
        "owner": [
            "user"
        ]
    }
},
{
    "model": "familybudgetapp.budget",
    "pk": 76,
    "fields": {
        "name": "Main",
        "description": null,
        "owner": [
            "user2"
        ]
    }
},
{
    "model": "familybudgetapp.budget",
    "pk": 77,
    "fields": {
        "name": "Savings",
        "description": null,
        "owner": [
            "user2"
        ]
    }
},
{
    "model": "familybudgetapp.budget",
    "pk": 78,
    "fields": {
        "name": "test",
        "description": "",
        "owner": [
            "user2"
        ]
    }
},
{
    "model": "familybudgetapp.budget",
    "pk": 79,
    "fields": {
        "name": "test",
        "description": "test",
        "owner": [
            "user"
        ]
    }
},
{
    "model": "familybudgetapp.budget",
    "pk": 80,
    "fields": {
        "name": "test",
        "description": "test",
        "owner": [
            "user"
        ]
    }
},
{
    "model": "familybudgetapp.budget",
    "pk": 81,
    "fields": {
        "name": "test",
        "description": "test",
        "owner": [
            "user"
        ]
    }
},
{
    "model": "familybudgetapp.budget",
    "pk": 82,
    "fields": {
        "name": "Budget example",
        "description": "budget",
        "owner": [
            "user"
        ]
    }
},
{
    "model": "familybudgetapp.category",
    "pk": 1,
    "fields": {
        "name": "Food"
    }
},
{
    "model": "familybudgetapp.category",
    "pk": 2,
    "fields": {
        "name": "Job"
    }
},
{
    "model": "familybudgetapp.category",
    "pk": 3,
    "fields": {
        "name": "Credit"
    }
},
{
    "model": "familybudgetapp.category",
    "pk": 4,
    "fields": {
        "name": "Savings"
    }
},
{
    "model": "familybudgetapp.category",
    "pk": 5,
    "fields": {
        "name": "Transportation"
    }
},
{
    "model": "familybudgetapp.transaction",
    "pk": 7,
    "fields": {
        "description": "Saving 1",
        "amount": 100,
        "transaction_type": "IN",
        "created_at": "2023-01-24",
        "category": 4,
        "budget": 78
    }
},
{
    "model": "familybudgetapp.transaction",
    "pk": 8,
    "fields": {
        "description": "Saving 2",
        "amount": 500,
        "transaction_type": "IN",
        "created_at": "2023-01-24",
        "category": 4,
        "budget": 74
    }
},
{
    "model": "familybudgetapp.transaction",
    "pk": 9,
    "fields": {
        "description": "Grocery",
        "amount": 50,
        "transaction_type": "EX",
        "created_at": "2023-01-24",
        "category": 1,
        "budget": 75
    }
},
{
    "model": "familybudgetapp.transaction",
    "pk": 10,
    "fields": {
        "description": "Paycheck",
        "amount": 2000,
        "transaction_type": "IN",
        "created_at": "2023-01-24",
        "category": 2,
        "budget": 75
    }
},
{
    "model": "familybudgetapp.transaction",
    "pk": 11,
    "fields": {
        "description": "Credit",
        "amount": 200,
        "transaction_type": "EX",
        "created_at": "2023-01-24",
        "category": 3,
        "budget": 76
    }
},
{
    "model": "familybudgetapp.transaction",
    "pk": 12,
    "fields": {
        "description": "Paycheck",
        "amount": 3000,
        "transaction_type": "IN",
        "created_at": "2023-01-24",
        "category": 2,
        "budget": 76
    }
},
{
    "model": "familybudgetapp.transaction",
    "pk": 13,
    "fields": {
        "description": "Gasoline",
        "amount": 300,
        "transaction_type": "EX",
        "created_at": "2023-01-24",
        "category": 5,
        "budget": 76
    }
},
{
    "model": "familybudgetapp.transaction",
    "pk": 14,
    "fields": {
        "description": "Expense example",
        "amount": 100,
        "transaction_type": "EX",
        "created_at": "2023-01-24",
        "category": 1,
        "budget": 76
    }
},
{
    "model": "familybudgetapp.transaction",
    "pk": 15,
    "fields": {
        "description": "Expense example",
        "amount": 100,
        "transaction_type": "EX",
        "created_at": "2023-01-24",
        "category": 1,
        "budget": 76
    }
},
{
    "model": "familybudgetapp.transaction",
    "pk": 16,
    "fields": {
        "description": "Expense example",
        "amount": 100,
        "transaction_type": "EX",
        "created_at": "2023-01-24",
        "category": 1,
        "budget": 76
    }
},
{
    "model": "familybudgetapp.shared",
    "pk": 2,
    "fields": {
        "shared_with": [
            "user2"
        ],
        "budget": 78
    }
},
{
    "model": "familybudgetapp.shared",
    "pk": 3,
    "fields": {
        "shared_with": [
            "user"
        ],
        "budget": 77
    }
},
{
    "model": "authtoken.token",
    "pk": "98f674d41408b9425d03ad5fd690e84e0aec42df",
    "fields": {
        "user": [
            "user2"
        ],
        "created": "2023-01-24T12:56:32.160Z"
    }
},
{
    "model": "authtoken.token",
    "pk": "b1199ee92738ede753e523f530a0440076a4d41a",
    "fields": {
        "user": [
            "user"
        ],
        "created": "2023-01-24T12:53:46.385Z"
    }
}
]